trackerping.py
trackerping-1.1.0.dist-info/licenses/LICENSE
trackerping-1.1.0.dist-info/METADATA
trackerping-1.1.0.dist-info/WHEEL
trackerping-1.1.0.dist-info/entry_points.txt
trackerping-1.1.0.dist-info/top_level.txt
trackerping-1.1.0.dist-info/RECORD
