Metadata-Version: 2.4
Name: trackerping
Version: 1.1.0
Summary: Connectivity test tool for Bittorrent trackers.
Author-email: Cycloctane <Cycloctane@octane.top>
License-Expression: MIT
Project-URL: Repository, https://github.com/Cycoctane/trackerping.git
Keywords: torrent,network
Classifier: Topic :: Utilities
Classifier: Development Status :: 4 - Beta
Classifier: Programming Language :: Python :: 3
Requires-Python: >=3.10
License-File: LICENSE
Requires-Dist: aiohttp>=3.11
Requires-Dist: anyio
Requires-Dist: yarl
Dynamic: license-file
